[
    {
        "nombre": "Fundamentos de programacion",
        "salon": {
            "1": {
                "trainer": [
                    {
                        "nombre": "Juan",
                        "apellido": "Carlos",
                        "tiempo": "dia"
                    }
                ],
                "tiempo": "dia",
                "capacidad": 33,
                "i": {
                    "camper": [
                        {
                            "nombre": "Camilo",
                            "apellido": "Navas",
                            "documento": "123456789",
                            "direccion": "Cra 9",
                            "acudiente": "Cris",
                            "telefono": "12345",
                            "estado": "inscrito",
                            "inicial": "Aprobado",
                            "rendimiento": "alto",
                            "riesgo": "bajo",
                            "atencion": "no",
                            "NotaFinal": 80.0,
                            "final": "Cursando"
                        },
                        {
                            "nombre": "Maria",
                            "apellido": "Medina",
                            "documento": "1235",
                            "direccion": "nose",
                            "acudiente": "rodolfo",
                            "telefono": "765",
                            "estado": "inscrito",
                            "inicial": "Aprobado",
                            "rendimiento": "alto",
                            "riesgo": "bajo",
                            "atencion": "no",
                            "NotaFinal": 90.0,
                            "final": "Cursando"
                        }
                    ]
                }
            },
            "2": {
                "trainer": []
            },
            "3": {
                "trainer": []
            }
        }
    }
]